f5_agent_auditor/__init__.py
f5_agent_auditor/auditor.py
f5_agent_auditor/filters.py
f5_agent_auditor/options.py
f5_agent_auditor/resource_helper.py
f5_agent_auditor/utils.py
f5_agent_auditor/collector/__init__.py
f5_agent_auditor/collector/base.py
f5_agent_auditor/collector/bigip_collector.py
f5_agent_auditor/collector/factory.py
f5_agent_auditor/collector/lbaas_collector.py
f5_agent_auditor/comparator/__init__.py
f5_agent_auditor/comparator/lbaas_bigip_comparator.py
f5_agent_auditor/db/__init__.py
f5_agent_auditor/db/connection.py
f5_agent_auditor/db/models.py
f5_agent_auditor/db/queries.py
f5_agent_auditor/publishers/__init__.py
f5_agent_auditor/publishers/csv_publisher.py
f5_agent_auditor/publishers/json_publisher.py
f5_agent_auditor-0.0.0.dist-info/METADATA
f5_agent_auditor-0.0.0.dist-info/WHEEL
f5_agent_auditor-0.0.0.dist-info/entry_points.txt
f5_agent_auditor-0.0.0.dist-info/top_level.txt
f5_agent_auditor-0.0.0.dist-info/RECORD
