Metadata-Version: 2.1
Name: f5-agent-auditor
Version: 0.0.0
Summary: A small check tool for F5 LBaas Agent
Home-page: https://github.com/zhang-shengping/f5-agent-auditor
Author: Peter Zhang
Author-email: peter.zhang@f5.com
License: UNKNOWN
Project-URL: Bug Tracker, https://github.com/zhang-shengping/f5-agent-auditor/issues
Platform: UNKNOWN
Classifier: Environment :: OpenStack
Classifier: Intended Audience :: System Administrators
Classifier: Intended Audience :: Information Technology
Classifier: License :: OSI Approved :: Apache Software License
Classifier: Operating System :: POSIX :: Linux
Classifier: Programming Language :: Python :: 2.7
Requires-Dist: f5-openstack-agent (>=9.6.0)
